odoo10_addon_l10n_es_account_group-10.0.1.0.0.99.dev5-py3.8-nspkg.pth
odoo/addons/l10n_es_account_group/README.rst
odoo/addons/l10n_es_account_group/__init__.py
odoo/addons/l10n_es_account_group/__manifest__.py
odoo/addons/l10n_es_account_group/data/account_account_template_assoc_data.xml
odoo/addons/l10n_es_account_group/data/account_account_template_common_data.xml
odoo/addons/l10n_es_account_group/data/account_account_template_full_data.xml
odoo/addons/l10n_es_account_group/data/account_account_template_pymes_data.xml
odoo/addons/l10n_es_account_group/data/account_group_data.xml
odoo/addons/l10n_es_account_group/i18n/l10n_es_account_group.pot
odoo/addons/l10n_es_account_group/readme/CONTRIBUTORS.rst
odoo/addons/l10n_es_account_group/readme/DESCRIPTION.rst
odoo/addons/l10n_es_account_group/readme/INSTALL.rst
odoo/addons/l10n_es_account_group/readme/ROADMAP.rst
odoo/addons/l10n_es_account_group/readme/USAGE.rst
odoo/addons/l10n_es_account_group/static/description/icon.png
odoo/addons/l10n_es_account_group/static/description/index.html
odoo10_addon_l10n_es_account_group-10.0.1.0.0.99.dev5.dist-info/METADATA
odoo10_addon_l10n_es_account_group-10.0.1.0.0.99.dev5.dist-info/WHEEL
odoo10_addon_l10n_es_account_group-10.0.1.0.0.99.dev5.dist-info/namespace_packages.txt
odoo10_addon_l10n_es_account_group-10.0.1.0.0.99.dev5.dist-info/top_level.txt
odoo10_addon_l10n_es_account_group-10.0.1.0.0.99.dev5.dist-info/RECORD
